intset.so
pyintset-0.1.5.dist-info/AUTHORS.rst
pyintset-0.1.5.dist-info/LICENSE
pyintset-0.1.5.dist-info/METADATA
pyintset-0.1.5.dist-info/WHEEL
pyintset-0.1.5.dist-info/top_level.txt
pyintset-0.1.5.dist-info/RECORD
