Metadata-Version: 2.1
Name: pyintset
Version: 0.1.5
Summary: UNKNOWN
Home-page: https://github.com/dzdx/pyintset
Author: dzdx
Author-email: dzidaxie@gmail.com
License: MIT license
Keywords: intset
Platform: any
Classifier: Development Status :: 2 - Pre-Alpha
Classifier: Intended Audience :: Developers
Classifier: License :: OSI Approved :: MIT License
Classifier: Natural Language :: English
Classifier: Programming Language :: Python :: 2.6
Classifier: Programming Language :: Python :: 2.7
Classifier: Programming Language :: Python :: 3
Classifier: Programming Language :: Python :: 3.3
Classifier: Programming Language :: Python :: 3.4
Classifier: Programming Language :: Python :: 3.5
